sheen/__init__.py
sheen/__main__.py
sheen/color.py
sheen/colored.py
sheen-0.1.2.dist-info/LICENSE
sheen-0.1.2.dist-info/METADATA
sheen-0.1.2.dist-info/WHEEL
sheen-0.1.2.dist-info/top_level.txt
sheen-0.1.2.dist-info/RECORD
